cvm_count.py
cvm_count-0.1.1.dist-info/LICENSE
cvm_count-0.1.1.dist-info/METADATA
cvm_count-0.1.1.dist-info/WHEEL
cvm_count-0.1.1.dist-info/RECORD
